{"nodes": [{"neighbors": ["10535"], "Floor": "", "inDegree": "0", "Cost Center": "661434060", "Official City": "Beijing", "Location": "11897", "Department": "Tech News Technology-CHN-RB3", "Official State": "", "id": "28105", "Title": "Principal Software Engineer", "Office Cube": "2316", "Address": "", "UTC Offset": "", "Hire Date": "", "Official Post Code": "100193", "outDegree": "1", "Official Country": "China", "totalDegree": "1", "predecessors": [], "Job Family": "", "Expertise": "", "successors": ["10535"]}, {"neighbors": ["28105"], "Floor": "", "inDegree": "1", "Cost Center": "241683408", "Official City": "London", "Location": "11197", "Department": "Tech News Technology-GBR-FEG", "Official State": "", "id": "10535", "Title": "Lead Technical Specialist, Collections", "Office Cube": "Desk 15", "Address": "", "UTC Offset": "", "Hire Date": "", "Official Post Code": "EC2A4EG", "outDegree": "0", "Official Country": "United Kingdom", "totalDegree": "1", "predecessors": ["28105"], "Job Family": "", "Expertise": "Software development: Ultra low latency; multi-threading;  high throughput; Windows. Networks and networking software development. C++ and C#. Man management. Architecture. Project management.\n680216,\n680217,...\n680218,", "successors": []}], "links": [{"rtime": ["1337676481566", "1337064162175", "1337066442933", "1337741437901", "1337064312389", "1337739225728", "1337152865249", "1336639718713"], "ltype": ["SGROUP", "SGROUP", "SGROUP", "SGROUP", "NOLOC", "SGROUP", "SGROUP", "SGROUP"], "target": "10535", "rtype": ["COM", "COM", "COM", "COM", "COM", "COM", "COM", "COM"], "ctype": ["DOC", "DOC", "DOC", "DOC", "COM", "DOC", "DOC", "DOC"], "lname": ["NfCP", "NfCP", "NfCP", "NfCP", "NONAME", "NfCP", "NfCP", "NfCP"], "source": "28105", "lcnt": {"NfCP": 7, "NONAME": 1}, "value": "8"}]}